chatmanager/__init__.py
chatmanager/config.py
chatmanager/core/__init__.py
chatmanager/core/chat.py
chatmanager/core/key.py
chatmanager/core/prompt.py
chatmanager/core/session.py
chatmanager/util/__init__.py
chatmanager/util/common.py
chatmanager/util/db.py
chatmanager/util/log.py
chatmanager/util/multi.py
chatmanager-0.0.1.dist-info/LICENSE
chatmanager-0.0.1.dist-info/METADATA
chatmanager-0.0.1.dist-info/WHEEL
chatmanager-0.0.1.dist-info/top_level.txt
chatmanager-0.0.1.dist-info/RECORD
