Metadata-Version: 2.1
Name: chatmanager
Version: 0.0.1
Summary: A tool collection to facilitate the use of ChatGPT API
Home-page: https://github.com/PeiweiHu/chatmanager
Author: Peiwei Hu
Author-email: jlu.hpw@foxmail.com
License: MIT
Classifier: Programming Language :: Python :: 3
Classifier: Operating System :: OS Independent
Requires-Python: >=3.8
License-File: LICENSE
Requires-Dist: openai
Requires-Dist: tiktoken
Requires-Dist: typeguard
